Year 1/COMP12111 Fundamentals of Computer Engineering/Exercise2/mu0_alu.v
// MU0 ALU design 
// P W Nutter (based on a design by Jeff Pepper)
// Date 2/9/2020
// 

// Do not touch the following line it is required for simulation 
`timescale 1ns/100ps

// for simulation purposes, do not delete
`default_nettype none

// module header

module mu0_alu(input  wire [15:0]  X, 
               input  wire [15:0]  Y, 
               input  wire [1:0]   M, 
               output reg  [15:0]  Q);

// behavioural description
always @(*) begin
    case (M[1:0])
        2'b00:    Q[15:0] = Y[15:0];
        2'b01:    Q[15:0] = X[15:0] + Y[15:0];
        2'b10:    Q[15:0] = X[15:0] + 1;
        2'b11:    Q[15:0] = X[15:0] - Y[15:0];
    endcase
  end
endmodule 

// for simulation purposes, do not delete
`default_nettype wire

Year 1/COMP12111 Fundamentals of Computer Engineering/Exercise2/mu0_alu_tb.v
// MU0 ALU testbench 
// P W Nutter (based on a design by Jeff Pepper)
// Date 2/9/2020
// 

// #1 = 1ns
`timescale 1ns/100ps 

module mu0_alu_tb();

// Internal connections
reg [15:0]  X; 
reg [15:0]  Y;
reg [1:0]   M;
wire  [15:0]  Q;

// Instantiate mu0_alu as dut (device under test)

mu0_alu dut(X, Y, M, Q);

// Test vectors
initial
begin
//Test
#100 X=16'h0000; Y=16'h0000; M=2'b00;

//M==00 Y
#100 X=16'h0000; Y=16'h000F; M=2'b00;//Test for Connection Y Y>0
#100 X=16'h0000; Y=16'hFFFF; M=2'b00;//Test for Y<0

//M==01 X + Y
#100 X=16'h000F; Y=16'h000F; M=2'b01;//Test for Y>0 X>0
#100 X=16'h000F; Y=16'hFFFF; M=2'b01;//Test for Y<0 X>0
#100 X=16'hFFFF; Y=16'h000F; M=2'b01;//Test for Y>0 X<0
#100 X=16'hFFFF; Y=16'hFFFF; M=2'b01;//Test for Y<0 X<0

//M==10 X + 1
#100 X=16'h000F; Y=16'h0000; M=2'b10;//Test for Connection X X>0
#100 X=16'hFFFF; Y=16'h0000; M=2'b10;//Test for X<0

//M==11 X - Y
#100 X=16'h000F; Y=16'h000F; M=2'b11;//Test for Y>0 X>0
#100 X=16'h000F; Y=16'hFFFF; M=2'b11;//Test for Y<0 X>0
#100 X=16'hFFFF; Y=16'h000F; M=2'b11;//Test for Y>0 X<0
#100 X=16'hFFFF; Y=16'hFFFF; M=2'b11;//Test for Y<0 X<0

#100 $finish;;   // end the simulation
end
 
// Save results as VCD file 
// Do not change
initial
 begin
  $dumpfile("mu0_alu_tb_results.vcd");  // Save simulation waveforms in this file
  $dumpvars; // Capture all simulation waveforms
 end

endmodule

Year 1/COMP12111 Fundamentals of Computer Engineering/Exercise2/mu0_alu_tb_results.vcd
$date
	Thu Nov  5 16:38:08 2020
$end
$version
	Icarus Verilog
$end
$timescale
	100ps
$end
$scope module mu0_alu_tb $end
$var wire 16 ! Q [15:0] $end
$var reg 2 " M [1:0] $end
$var reg 16 # X [15:0] $end
$var reg 16 $ Y [15:0] $end
$scope module dut $end
$var wire 2 % M [1:0] $end
$var wire 16 & X [15:0] $end
$var wire 16 ' Y [15:0] $end
$var reg 16 ( Q [15:0] $end
$upscope $end
$upscope $end
$enddefinitions $end
#0
$dumpvars
bx (
bx '
bx &
bx %
bx $
bx #
bx "
bx !
$end
#1000
b0 !
b0 (
b0 "
b0 %
b0 $
b0 '
b0 #
b0 &
#2000
b1111 !
b1111 (
b1111 $
b1111 '
#3000
b1111111111111111 !
b1111111111111111 (
b1111111111111111 $
b1111111111111111 '
#4000
b11110 !
b11110 (
b1 "
b1 %
b1111 $
b1111 '
b1111 #
b1111 &
#5000
b1110 !
b1110 (
b1111111111111111 $
b1111111111111111 '
#6000
b1111 $
b1111 '
b1111111111111111 #
b1111111111111111 &
#7000
b1111111111111110 !
b1111111111111110 (
b1111111111111111 $
b1111111111111111 '
#8000
b10000 !
b10000 (
b10 "
b10 %
b0 $
b0 '
b1111 #
b1111 &
#9000
b0 !
b0 (
b1111111111111111 #
b1111111111111111 &
#10000
b11 "
b11 %
b1111 $
b1111 '
b1111 #
b1111 &
#11000
b10000 !
b10000 (
b1111111111111111 $
b1111111111111111 '
#12000
b1111111111110000 !
b1111111111110000 (
b1111 $
b1111 '
b1111111111111111 #
b1111111111111111 &
#13000
b0 !
b0 (
b1111111111111111 $
b1111111111111111 '
