Year 1/COMP12111 Fundamentals of Computer Engineering/Exercise3/mu0_decode.v
// MU0 decode design - behavioural style
// P W Nutter (based on a design by Jeff Pepper)
// Date 2/9/2020
// 

// Do not touch the following line it is required for simulation 
`timescale 1ns/100ps

// for simulation purposes, do not delete
`default_nettype none

// module definition

module mu0_decode(input  wire        state,      // System clock
                  input  wire [3:0]  F,          // Bits [15:12] of the IR
                  input  wire        N,          // Negative flag
                  input  wire        Z,          // Zero flag
                  output reg         fetch,      // Used for debug
                  output reg         PC_En,      // Update PC
                  output reg         IR_En,      // Update IR
                  output reg         Acc_En,     // Update Acc
                  output reg         X_sel,      // Data Out mux(X port on ALU) 0 for Acc, 1 for PC
                  output reg         Y_sel,      // mux, Y port on ALU, 0 for Data In, 1 for Instr 
                  output reg         Addr_sel,   // mux, 0 for PC, 1 for IR
                  output reg  [1:0]  M,          // ALU op, 0) Y, 1) X+Y, 2) X+1, 3) X-Y
                  output reg         Rd,         // Memory read
                  output reg         Wr,         // Memory write
                  output reg         Halted);    // MU0 stopped


// Control decode
always @ (*) begin
    if (~state) begin // Fetch Stage
        fetch = 1'b1;
        PC_En = 1'b1;
        IR_En = 1'b1;
        Acc_En = 1'b0;
        M = 2'b10;
        X_sel = 1'b1;
        Y_sel = 1'hx;
        Addr_sel = 1'b0;
        Rd = 1'b1;
        Wr = 1'b0;
        Halted = 1'b0;
        end
    else if (state) begin// LDA
        fetch = 1'b0;
        case (F)
            3'b000: begin 
                        PC_En = 1'b0;
                        IR_En = 1'b0;
                        Acc_En = 1'b1;
                        M = 2'b00;
                        X_sel = 1'hx;
                        Y_sel = 1'b0;
                        Addr_sel = 1'b1;
                        Rd = 1'b1;
                        Wr = 1'b0;
                        Halted = 1'b0;
                        end
            3'b001: begin // STA
                        PC_En = 1'b0;
                        IR_En = 1'b0;
                        Acc_En = 1'b0;
                        M = 2'hx;
                        X_sel = 1'b0;
                        Y_sel = 1'hx;
                        Addr_sel = 1'b1;
                        Rd = 1'b0;
                        Wr = 1'b1;
                        Halted = 1'b0;
                        end
            3'b010: begin // ADD
                        PC_En = 1'b0;
                        IR_En = 1'b0;
                        Acc_En = 1'b1;
                        M = 2'b01;
                        X_sel = 1'b0;
                        Y_sel = 1'b0;
                        Addr_sel = 1'b1;
                        Rd = 1'b1;
                        Wr = 1'b0;
                        Halted = 1'b0;
                        end
            3'b011: begin // SUB
                        PC_En = 1'b0;
                        IR_En = 1'b0;
                        Acc_En = 1'b1;
                        M = 2'b11;
                        X_sel = 1'b0;
                        Y_sel = 1'b0;
                        Addr_sel = 1'b1;
                        Rd = 1'b1;
                        Wr = 1'b0;
                        Halted = 1'b0;
                        end
            3'b100: begin // JMP
                        PC_En = 1'b1;
                        IR_En = 1'b0;
                        Acc_En = 1'b0;
                        M = 2'b00;
                        X_sel = 1'hx;
                        Y_sel = 1'b1;
                        Addr_sel = 1'hx;
                        Rd = 1'b0;
                        Wr = 1'b0;
                        Halted = 1'b0;
                        end
            3'b101: begin // JGE
                        if (~N) begin // JMP if not negative
                            PC_En = 1'b1;
                            IR_En = 1'b0;
                            Acc_En = 1'b0;
                            M = 2'b00;
                            X_sel = 1'hx;
                            Y_sel = 1'b1;
                            Addr_sel = 1'hx;
                            Rd = 1'b0;
                            Wr = 1'b0;
                            Halted = 1'b0;
                            end
                        else begin
                            PC_En = 1'b0;
                            IR_En = 1'b0;
                            Acc_En = 1'b0;
                            M = 2'hx;
                            X_sel = 1'hx;
                            Y_sel = 1'hx;
                            Addr_sel = 1'hx;
                            Rd = 1'b0;
                            Wr = 1'b0;
                            Halted = 1'b0;
                            end
                            end
            3'b110: begin // JNE
                        if (~Z) begin // JMP if not zero
                            PC_En = 1'b1;
                            IR_En = 1'b0;
                            Acc_En = 1'b0;
                            M = 2'b00;
                            X_sel = 1'hx;
                            Y_sel = 1'b1;
                            Addr_sel = 1'hx;
                            Rd = 1'b0;
                            Wr = 1'b0;
                            Halted = 1'b0;
                            end
                        else begin
                            PC_En = 1'b0;
                            IR_En = 1'b0;
                            Acc_En = 1'b0;
                            M = 2'hx;
                            X_sel = 1'hx;
                            Y_sel = 1'hx;
                            Addr_sel = 1'hx;
                            Rd = 1'b0;
                            Wr = 1'b0;
                            Halted = 1'b0;
                            end
                            end
            3'b111: begin // STP
                        PC_En = 1'b0;
                        IR_En = 1'b0;
                        Acc_En = 1'b0;
                        M = 2'hx;
                        X_sel = 1'hx;
                        Y_sel = 1'hx;
                        Addr_sel = 1'hx;
                        Rd = 1'b0;
                        Wr = 1'b0;
                        Halted = 1'b1;
                        end
            default: begin // Invalid Instruction
                        PC_En = 1'b0;
                        IR_En = 1'b0;
                        Acc_En = 1'b0;
                        M = 2'hx;
                        X_sel = 1'hx;
                        Y_sel = 1'hx;
                        Addr_sel = 1'hx;
                        Rd = 1'b0;
                        Wr = 1'b0;
                        Halted = 1'b0;
                        end
            endcase
        end
        else // Invalid State
            begin
                PC_En = 1'b0;
                IR_En = 1'b0;
                Acc_En = 1'b0;
                M = 2'hx;
                X_sel = 1'hx;
                Y_sel = 1'hx;
                Addr_sel = 1'hx;
                Rd = 1'b0;
                Wr = 1'b0;
                Halted = 1'b0;
                end
end
endmodule 

// for simulation purposes, do not delete
`default_nettype wire

Year 1/COMP12111 Fundamentals of Computer Engineering/Exercise3/mu0_fsm.v
// MU0 FSM design - behavioural style
// P W Nutter (based on a design by Jeff Pepper)
// Date 2/9/2020
// 

// Do not touch the following line it is required for simulation 
`timescale 1ns/100ps

// for simulation purposes, do not delete
`default_nettype none

// module header

module mu0_fsm(input  wire         Clk, 
	           input  wire         Reset, 
			   input  wire         Halted, 
			   output reg          state);

// internal variables
reg next_state;

// Behavioural description
always @ (*)
    case (state)
        1'b0:       next_state = 1'b1;
        default:    next_state = 1'b0;
    endcase



always @ (posedge Clk, posedge Reset) // Asynchronous Reset
    if (Reset)
        state <= 1'b0;
    else if(~Halted)
        state <= next_state;

endmodule 

// for simulation purposes, do not delete
`default_nettype wire

Year 1/COMP12111 Fundamentals of Computer Engineering/Exercise3/mu0_control.v
// MU0 control design - behavioural style
// P W Nutter (based on a design by Jeff Pepper)
// Date 2/9/2020
// 

// Do not touch the following line it is required for simulation 
`timescale 1ns/100ps

// for simulation purposes, do not delete
`default_nettype none

// module definition

module mu0_control(input  wire         Clk,      // System clock
                   input  wire         Reset,    // System reset
                   input  wire  [3:0]  F,        // Bits [15:12] of the IR
                   input  wire         N,        // Negative flag
                   input  wire         Z,        // Zero flag
                   output wire          fetch,    // Used for debug
                   output wire          PC_En,    // Update PC
                   output wire          IR_En,    // Update IR
                   output wire          Acc_En,   // Update Acc
                   output wire          X_sel,    // Data Out mux(X port on ALU) 0 for Acc, 1 for PC
                   output wire          Y_sel,    // mux, Y port on ALU, 0 for Data In, 1 for Instr 
                   output wire          Addr_sel, // mux, 0 for PC, 1 for IR
                   output wire   [1:0]  M,        // ALU op, 0) Y, 1) X+Y, 2) X+1, 3) X-Y
                   output wire          Rd,       // Memory read
                   output wire          Wr,       // Memory write
                   output wire          Halted);  // MU0 stopped


//Internal signals
wire state;

// Instantiate MU0 FSM
// Uses explicit dot pins - safer than position substitution
mu0_fsm fsm(Clk, Reset, Halted, state);

// Instantiate Control decode
mu0_decode decode(state, F, N, Z, fetch, PC_En, IR_En, Acc_En, X_sel, Y_sel, Addr_sel, M, Rd, Wr, Halted);


endmodule 

// for simulation purposes, do not delete
`default_nettype wire

Year 1/COMP12111 Fundamentals of Computer Engineering/Exercise3/mu0_control_tb.v
// MU0 Control testbench
// P W Nutter (based on a design by Jeff Pepper)
// Date 2/9/2020
// 

// Do not touch the following line it is required for simulation 
`timescale 1ns/100ps 

module mu0_control_tb();

// Internal connections
reg Clk;
reg Reset;
reg [3:0]F;
reg N;
reg Z;
wire fetch;
wire PC_En;
wire IR_En;
wire Acc_En;
wire X_sel;
wire Y_sel;
wire addr_sel;
wire [1:0]M;
wire Rd;
wire Wr;
wire Halted;

// Instantiate mu0 control as dut (device under test)

mu0_control dut(
.Clk (Clk),
.Reset (Reset),
.F (F),
.N (N),
.Z (Z),
.fetch (fetch),
.PC_En (PC_En),
.IR_En (IR_En),
.Acc_En (Acc_En),
.X_sel (X_sel),
.Y_sel (Y_sel),
.Addr_sel (Addr_sel),
.M (M),
.Rd (Rd),
.Wr (Wr),
.Halted (Halted));


// Set up the clock

initial Clk = 0;
always
    begin
    #50
    Clk = ~Clk;
    end

// Test vectors
// Using #200 to make sure that we go through both fetch and execute
initial
begin
    #150    // Test for Clk
    Reset = 1; N = 0; Z = 0;
    #50 Reset = 0;
    #150    // Test for fetch execute cycle
    #100 F = 3'b000;            // Test LDA
    #100                   
    #100 F = 3'b001;            // Test STA
    #100
    #100 F = 3'b010;            // Test ADD
    #100
    #100 F = 3'b011;            // Test SUB
    #100
    #100 F = 3'b100;            // Test JMP
    #100
    #100 F = 3'b101; N = 0;     // Test JGE when N = 0
    #100
    #100 F = 3'b101; N = 1;     // Test JGE when N = 1
    #100
    #100 F = 3'b110; Z = 0;     // Test JNE when Z = 0
    #100
    #100 F = 3'b110; Z = 1;     // Test JNE when Z = 1
    #100
    #100 F = 3'b111;            // Test STP
    #100
    #100 Reset = 1;             // Test Reset in Execute state
    #100
  $finish;   // end the simulation
end

 
// Save results as VCD file 
// Do not change
initial
 begin
  $dumpfile("mu0_control_tb_results.vcd");  // Save simulation waveforms in this file
  $dumpvars; // Capture all simulation waveforms
 end

endmodule

Year 1/COMP12111 Fundamentals of Computer Engineering/Exercise3/mu0_control_tb_results.vcd
$date
	Wed Dec  9 06:31:56 2020
$end
$version
	Icarus Verilog
$end
$timescale
	100ps
$end
$scope module mu0_control_tb $end
$var wire 1 ! fetch $end
$var wire 1 " Y_sel $end
$var wire 1 # X_sel $end
$var wire 1 $ Wr $end
$var wire 1 % Rd $end
$var wire 1 & PC_En $end
$var wire 2 ' M [1:0] $end
$var wire 1 ( IR_En $end
$var wire 1 ) Halted $end
$var wire 1 * Addr_sel $end
$var wire 1 + Acc_En $end
$var reg 1 , Clk $end
$var reg 4 - F [3:0] $end
$var reg 1 . N $end
$var reg 1 / Reset $end
$var reg 1 0 Z $end
$scope module dut $end
$var wire 1 , Clk $end
$var wire 4 1 F [3:0] $end
$var wire 1 . N $end
$var wire 1 / Reset $end
$var wire 1 0 Z $end
$var wire 1 2 state $end
$var wire 1 ! fetch $end
$var wire 1 " Y_sel $end
$var wire 1 # X_sel $end
$var wire 1 $ Wr $end
$var wire 1 % Rd $end
$var wire 1 & PC_En $end
$var wire 2 3 M [1:0] $end
$var wire 1 ( IR_En $end
$var wire 1 ) Halted $end
$var wire 1 * Addr_sel $end
$var wire 1 + Acc_En $end
$scope module decode $end
$var wire 4 4 F [3:0] $end
$var wire 1 . N $end
$var wire 1 0 Z $end
$var wire 1 2 state $end
$var reg 1 + Acc_En $end
$var reg 1 * Addr_sel $end
$var reg 1 ) Halted $end
$var reg 1 ( IR_En $end
$var reg 2 5 M [1:0] $end
$var reg 1 & PC_En $end
$var reg 1 % Rd $end
$var reg 1 $ Wr $end
$var reg 1 # X_sel $end
$var reg 1 " Y_sel $end
$var reg 1 ! fetch $end
$upscope $end
$scope module fsm $end
$var wire 1 , Clk $end
$var wire 1 ) Halted $end
$var wire 1 / Reset $end
$var reg 1 6 next_state $end
$var reg 1 2 state $end
$upscope $end
$upscope $end
$upscope $end
$enddefinitions $end
#0
$dumpvars
x6
bx 5
bx 4
bx 3
x2
bx 1
x0
x/
x.
bx -
0,
x+
x*
x)
x(
bx '
x&
x%
x$
x#
x"
x!
$end
#500
1,
#1000
0,
#1500
0*
1#
b10 '
b10 3
b10 5
1!
16
02
0)
0$
1%
0+
1(
1&
1,
00
0.
1/
#2000
0,
0/
#2500
0%
x*
x#
bx '
bx 3
bx 5
0(
0&
0!
06
12
1,
#3000
0,
#3500
1%
0*
1#
b10 '
b10 3
b10 5
1(
1&
1!
16
02
1,
#4000
0,
#4500
1*
0"
x#
b0 '
b0 3
b0 5
1+
0(
0&
0!
06
12
1,
b0 -
b0 1
b0 4
#5000
0,
#5500
0*
x"
1#
b10 '
b10 3
b10 5
0+
1(
1&
1!
16
02
1,
#6000
0,
#6500
1$
0%
1*
0#
bx '
bx 3
bx 5
0(
0&
0!
06
12
1,
b1 -
b1 1
b1 4
#7000
0,
#7500
0$
1%
0*
1#
b10 '
b10 3
b10 5
1(
1&
1!
16
02
1,
#8000
0,
#8500
1*
0"
0#
b1 '
b1 3
b1 5
1+
0(
0&
0!
06
12
1,
b10 -
b10 1
b10 4
#9000
0,
#9500
0*
x"
1#
b10 '
b10 3
b10 5
0+
1(
1&
1!
16
02
1,
#10000
0,
#10500
1*
0"
0#
b11 '
b11 3
b11 5
1+
0(
0&
0!
06
12
1,
b11 -
b11 1
b11 4
#11000
0,
#11500
0*
x"
1#
b10 '
b10 3
b10 5
0+
1(
1&
1!
16
02
1,
#12000
0,
#12500
0%
x*
1"
x#
b0 '
b0 3
b0 5
0(
0!
06
12
1,
b100 -
b100 1
b100 4
#13000
0,
#13500
1%
0*
x"
1#
b10 '
b10 3
b10 5
1(
1!
16
02
1,
#14000
0,
#14500
0%
x*
1"
x#
b0 '
b0 3
b0 5
0(
0!
06
12
1,
b101 -
b101 1
b101 4
#15000
0,
#15500
1%
0*
x"
1#
b10 '
b10 3
b10 5
1(
1!
16
02
1,
#16000
0,
#16500
0%
x*
x#
bx '
bx 3
bx 5
0(
0&
0!
06
12
1,
1.
#17000
0,
#17500
1%
0*
1#
b10 '
b10 3
b10 5
1(
1&
1!
16
02
1,
#18000
0,
#18500
0%
x*
1"
x#
b0 '
b0 3
b0 5
0(
0!
06
12
1,
b110 -
b110 1
b110 4
#19000
0,
#19500
1%
0*
x"
1#
b10 '
b10 3
b10 5
1(
1!
16
02
1,
#20000
0,
#20500
0%
x*
x#
bx '
bx 3
bx 5
0(
0&
0!
06
12
1,
10
#21000
0,
#21500
1%
0*
1#
b10 '
b10 3
b10 5
1(
1&
1!
16
02
1,
#22000
0,
#22500
1)
0%
x*
x#
bx '
bx 3
bx 5
0(
0&
0!
06
12
1,
b111 -
b111 1
b111 4
#23000
0,
#23500
1,
#24000
0,
#24500
0)
1%
0*
1#
b10 '
b10 3
b10 5
1(
1&
1!
16
02
1,
1/
