Year 1/COMP12111 Fundamentals of Computer Engineering/Exercise3/mu0_fsm.v
// MU0 FSM design - behavioural style
// P W Nutter (based on a design by Jeff Pepper)
// Date 2/9/2020
// 

// Do not touch the following line it is required for simulation 
`timescale 1ns/100ps

// for simulation purposes, do not delete
`default_nettype none

// module header

module mu0_fsm(input  wire         Clk, 
	           input  wire         Reset, 
			   input  wire         Halted, 
			   output reg          state);

// internal variables
reg next_state;

// Behavioural description
always @ (*)
    case (state)
        1'b0:       next_state = 1'b1;
        default:    next_state = 1'b0;
    endcase



always @ (posedge Clk, posedge Reset) // Asynchronous Reset
    if (Reset)
        state <= 1'b0;
    else if(~Halted)
        state <= next_state;

endmodule 

// for simulation purposes, do not delete
`default_nettype wire

Year 1/COMP12111 Fundamentals of Computer Engineering/Exercise3/mu0_fsm_tb.v
// MU0 FSM testbench
// P W Nutter (based on a design by Jeff Pepper)
// Date 2/9/2020
// 

// Do not touch the following line it is required for simulation 
`timescale 1ns/100ps 

// module header

module mu0_fsm_tb();

// Internal connections
reg Clk;
reg Reset;
reg Halted;
wire state;

// Instantiate mu0 fsm as dut (device under test)
// Uses explicit dot pins - safer than position substitution

mu0_fsm dut(
.Clk (Clk),
.Reset (Reset),
.Halted (Halted),
.state (state));

// Set up the clock
initial Clk = 0;
always
    begin
    #50
    Clk = ~Clk;
    end

// Test vectors
initial
begin
    #100                // Test for Clk Signal
    Reset = 1; Halted = 0;    
    #50 Reset = 0;       
    #150                // Test if state change from 0 to 1 to 0
    #100 Reset = 1;     // Test Asynchronous Reset
    #50
    Reset = 0;  
    Halted = 1;         // Halted at Fetch
    #100
    Halted = 0;
    #50
    Halted = 1;         //Halted at Execute
    #100
    $finish;        // end the simulation
end
 
// Save results as VCD file 
// Do not change
initial
 begin
  $dumpfile("mu0_fsm_tb_results.vcd");  // Save simulation waveforms in this file
  $dumpvars; // Capture all simulation waveforms
 end

endmodule

Year 1/COMP12111 Fundamentals of Computer Engineering/Exercise3/mu0_fsm_tb_results.vcd
$date
	Fri Dec  4 10:19:27 2020
$end
$version
	Icarus Verilog
$end
$timescale
	100ps
$end
$scope module mu0_fsm_tb $end
$var wire 1 ! state $end
$var reg 1 " Clk $end
$var reg 1 # Halted $end
$var reg 1 $ Reset $end
$scope module dut $end
$var wire 1 " Clk $end
$var wire 1 # Halted $end
$var wire 1 $ Reset $end
$var reg 1 % next_state $end
$var reg 1 ! state $end
$upscope $end
$upscope $end
$enddefinitions $end
#0
$dumpvars
x%
x$
x#
0"
x!
$end
#500
1"
#1000
1%
0!
0"
0#
1$
#1500
0%
1!
1"
0$
#2000
0"
#2500
1%
0!
1"
#3000
0"
#3500
0%
1!
1"
#4000
1%
0!
0"
1$
#4500
1"
1#
0$
#5000
0"
#5500
0%
1!
1"
0#
#6000
0"
1#
