Year 1/COMP12111 Fundamentals of Computer Engineering/Exercise3/mu0_decode.v
// MU0 decode design - behavioural style
// P W Nutter (based on a design by Jeff Pepper)
// Date 2/9/2020
// 

// Do not touch the following line it is required for simulation 
`timescale 1ns/100ps

// for simulation purposes, do not delete
`default_nettype none

// module definition

module mu0_decode(input  wire        state,      // System clock
                  input  wire [3:0]  F,          // Bits [15:12] of the IR
                  input  wire        N,          // Negative flag
                  input  wire        Z,          // Zero flag
                  output reg         fetch,      // Used for debug
                  output reg         PC_En,      // Update PC
                  output reg         IR_En,      // Update IR
                  output reg         Acc_En,     // Update Acc
                  output reg         X_sel,      // Data Out mux(X port on ALU) 0 for Acc, 1 for PC
                  output reg         Y_sel,      // mux, Y port on ALU, 0 for Data In, 1 for Instr 
                  output reg         Addr_sel,   // mux, 0 for PC, 1 for IR
                  output reg  [1:0]  M,          // ALU op, 0) Y, 1) X+Y, 2) X+1, 3) X-Y
                  output reg         Rd,         // Memory read
                  output reg         Wr,         // Memory write
                  output reg         Halted);    // MU0 stopped


// Control decode
always @ (*) begin
    if (~state) begin // Fetch Stage
        fetch = 1'b1;
        PC_En = 1'b1;
        IR_En = 1'b1;
        Acc_En = 1'b0;
        M = 2'b10;
        X_sel = 1'b1;
        Y_sel = 1'hx;
        Addr_sel = 1'b0;
        Rd = 1'b1;
        Wr = 1'b0;
        Halted = 1'b0;
        end
    else if (state) begin// LDA
        fetch = 1'b0;
        case (F)
            3'b000: begin 
                        PC_En = 1'b0;
                        IR_En = 1'b0;
                        Acc_En = 1'b1;
                        M = 2'b00;
                        X_sel = 1'hx;
                        Y_sel = 1'b0;
                        Addr_sel = 1'b1;
                        Rd = 1'b1;
                        Wr = 1'b0;
                        Halted = 1'b0;
                        end
            3'b001: begin // STA
                        PC_En = 1'b0;
                        IR_En = 1'b0;
                        Acc_En = 1'b0;
                        M = 2'hx;
                        X_sel = 1'b0;
                        Y_sel = 1'hx;
                        Addr_sel = 1'b1;
                        Rd = 1'b0;
                        Wr = 1'b1;
                        Halted = 1'b0;
                        end
            3'b010: begin // ADD
                        PC_En = 1'b0;
                        IR_En = 1'b0;
                        Acc_En = 1'b1;
                        M = 2'b01;
                        X_sel = 1'b0;
                        Y_sel = 1'b0;
                        Addr_sel = 1'b1;
                        Rd = 1'b1;
                        Wr = 1'b0;
                        Halted = 1'b0;
                        end
            3'b011: begin // SUB
                        PC_En = 1'b0;
                        IR_En = 1'b0;
                        Acc_En = 1'b1;
                        M = 2'b11;
                        X_sel = 1'b0;
                        Y_sel = 1'b0;
                        Addr_sel = 1'b1;
                        Rd = 1'b1;
                        Wr = 1'b0;
                        Halted = 1'b0;
                        end
            3'b100: begin // JMP
                        PC_En = 1'b1;
                        IR_En = 1'b0;
                        Acc_En = 1'b0;
                        M = 2'b00;
                        X_sel = 1'hx;
                        Y_sel = 1'b1;
                        Addr_sel = 1'hx;
                        Rd = 1'b0;
                        Wr = 1'b0;
                        Halted = 1'b0;
                        end
            3'b101: begin // JGE
                        if (~N) begin // JMP if not negative
                            PC_En = 1'b1;
                            IR_En = 1'b0;
                            Acc_En = 1'b0;
                            M = 2'b00;
                            X_sel = 1'hx;
                            Y_sel = 1'b1;
                            Addr_sel = 1'hx;
                            Rd = 1'b0;
                            Wr = 1'b0;
                            Halted = 1'b0;
                            end
                        else begin
                            PC_En = 1'b0;
                            IR_En = 1'b0;
                            Acc_En = 1'b0;
                            M = 2'hx;
                            X_sel = 1'hx;
                            Y_sel = 1'hx;
                            Addr_sel = 1'hx;
                            Rd = 1'b0;
                            Wr = 1'b0;
                            Halted = 1'b0;
                            end
                            end
            3'b110: begin // JNE
                        if (~Z) begin // JMP if not zero
                            PC_En = 1'b1;
                            IR_En = 1'b0;
                            Acc_En = 1'b0;
                            M = 2'b00;
                            X_sel = 1'hx;
                            Y_sel = 1'b1;
                            Addr_sel = 1'hx;
                            Rd = 1'b0;
                            Wr = 1'b0;
                            Halted = 1'b0;
                            end
                        else begin
                            PC_En = 1'b0;
                            IR_En = 1'b0;
                            Acc_En = 1'b0;
                            M = 2'hx;
                            X_sel = 1'hx;
                            Y_sel = 1'hx;
                            Addr_sel = 1'hx;
                            Rd = 1'b0;
                            Wr = 1'b0;
                            Halted = 1'b0;
                            end
                            end
            3'b111: begin // STP
                        PC_En = 1'b0;
                        IR_En = 1'b0;
                        Acc_En = 1'b0;
                        M = 2'hx;
                        X_sel = 1'hx;
                        Y_sel = 1'hx;
                        Addr_sel = 1'hx;
                        Rd = 1'b0;
                        Wr = 1'b0;
                        Halted = 1'b1;
                        end
            default: begin // Invalid Instruction
                        PC_En = 1'b0;
                        IR_En = 1'b0;
                        Acc_En = 1'b0;
                        M = 2'hx;
                        X_sel = 1'hx;
                        Y_sel = 1'hx;
                        Addr_sel = 1'hx;
                        Rd = 1'b0;
                        Wr = 1'b0;
                        Halted = 1'b0;
                        end
            endcase
        end
        else // Invalid State
            begin
                PC_En = 1'b0;
                IR_En = 1'b0;
                Acc_En = 1'b0;
                M = 2'hx;
                X_sel = 1'hx;
                Y_sel = 1'hx;
                Addr_sel = 1'hx;
                Rd = 1'b0;
                Wr = 1'b0;
                Halted = 1'b0;
                end
end
endmodule 

// for simulation purposes, do not delete
`default_nettype wire

Year 1/COMP12111 Fundamentals of Computer Engineering/Exercise3/mu0_decode_tb.v
// MU0 Decode testbench
// P W Nutter (based on a design by Jeff Pepper)
// Date 2/9/2020
// 

// Do not touch the following line it is required for simulation 
`timescale 1ns/100ps 

module mu0_decode_tb();

// Internal connections
reg state;
reg [3:0]F;
reg N;
reg Z;
wire fetch;
wire PC_En;
wire IR_En;
wire Acc_En;
wire X_sel;
wire Y_sel;
wire Addr_sel;
wire [1:0]M;
wire Rd;
wire Wr;
wire Halted;

// Instantiate mu0 control as dut (device under test)
// Uses explicit dot pins - safer than position substitution
mu0_decode dut(
.state (state),
.F (F),
.N (N),
.Z (Z),
.fetch (fetch),
.PC_En (PC_En),
.IR_En (IR_En),
.Acc_En (Acc_En),
.X_sel (X_sel),
.Y_sel (Y_sel),
.Addr_sel (Addr_sel),
.M (M),
.Rd (Rd),
.Wr (Wr),
.Halted (Halted));

// Test vectors
// Make sure that we go through both fetch and execute
initial
begin
  state = 0;
  #100 state = 1; F=3'b000;       // Test for LDA
  #100 state = 1; F=3'b001;       // Test for STA
  #100 state = 1; F=3'b010;       // Test for ADD
  #100 state = 1; F=3'b011;       // Test for SUB
  #100 state = 1; F=3'b100;       // Test for JMP
  #100 state = 1; F=3'b101; N=0;  // Test for JGE when N = 0
  #100 state = 1; F=3'b101; N=1;  // Test for JGE when N = 1  
  #100 state = 1; F=3'b110; Z=0;  // Test for JNE when Z = 0
  #100 state = 1; F=3'b110; Z=1;  // Test for JNE when Z = 1
  #100 state = 1; F=3'b111;       // Test for STP
  #100
  $finish;   // end the simulation
end

 
// Save results as VCD file 
// Do not change
initial
 begin
  $dumpfile("mu0_decode_tb_results.vcd");  // Save simulation waveforms in this file
  $dumpvars; // Capture all simulation waveforms
 end

endmodule

Year 1/COMP12111 Fundamentals of Computer Engineering/Exercise3/mu0_decode_tb_results.vcd
$date
	Wed Dec  9 06:30:20 2020
$end
$version
	Icarus Verilog
$end
$timescale
	100ps
$end
$scope module mu0_decode_tb $end
$var wire 1 ! fetch $end
$var wire 1 " Y_sel $end
$var wire 1 # X_sel $end
$var wire 1 $ Wr $end
$var wire 1 % Rd $end
$var wire 1 & PC_En $end
$var wire 2 ' M [1:0] $end
$var wire 1 ( IR_En $end
$var wire 1 ) Halted $end
$var wire 1 * Addr_sel $end
$var wire 1 + Acc_En $end
$var reg 4 , F [3:0] $end
$var reg 1 - N $end
$var reg 1 . Z $end
$var reg 1 / state $end
$scope module dut $end
$var wire 4 0 F [3:0] $end
$var wire 1 - N $end
$var wire 1 . Z $end
$var wire 1 / state $end
$var reg 1 + Acc_En $end
$var reg 1 * Addr_sel $end
$var reg 1 ) Halted $end
$var reg 1 ( IR_En $end
$var reg 2 1 M [1:0] $end
$var reg 1 & PC_En $end
$var reg 1 % Rd $end
$var reg 1 $ Wr $end
$var reg 1 # X_sel $end
$var reg 1 " Y_sel $end
$var reg 1 ! fetch $end
$upscope $end
$upscope $end
$enddefinitions $end
#0
$dumpvars
b10 1
bx 0
0/
x.
x-
bx ,
0+
0*
0)
1(
b10 '
1&
1%
0$
1#
x"
1!
$end
#1000
1*
0"
x#
b0 '
b0 1
1+
0(
0&
0!
b0 ,
b0 0
1/
#2000
1$
0%
x"
0#
bx '
bx 1
0+
b1 ,
b1 0
#3000
0$
1%
0"
b1 '
b1 1
1+
b10 ,
b10 0
#4000
b11 '
b11 1
b11 ,
b11 0
#5000
0%
x*
1"
x#
b0 '
b0 1
0+
1&
b100 ,
b100 0
#6000
0-
b101 ,
b101 0
#7000
x"
bx '
bx 1
0&
1-
#8000
1"
b0 '
b0 1
1&
0.
b110 ,
b110 0
#9000
x"
bx '
bx 1
0&
1.
#10000
1)
b111 ,
b111 0
