Year 1/COMP12111 Fundamentals of Computer Engineering/Exercise1/full_adder.v
// Full adder design using verilog primitive gates
// P W Nutter (based on a design by Jeff Pepper)
// Date 1/9/2020
// 

// Do not touch the following line it is required for simulation 
// All gates have a 1ns delay (#1 = 1ns)
`timescale 1ns/100ps

// for simulation purposes, do not delete
`default_nettype none

//Module definition

module full_adder(input  wire  a, 
                  input  wire  b, 
                  input  wire  cin, 
                  output wire  s, 
                  output wire  cout);

//Internal connections should be specified here
wire axorb;
wire ab;
wire cin_axorb;

// Sum logic for full adder s=(a^b)^cin
xor #1 gate1(axorb,a,b);
xor #1 gate2(s,axorb,cin);

// Carry logic for full adder cout=cin.(a^b) + a.b
and #1 gate3(cin_axorb,axorb,cin);
and #1 gate4(ab,a,b);
or  #1 gate5(cout,cin_axorb,ab);



endmodule 

// for simulation purposes, do not delete
`default_nettype wire

Year 1/COMP12111 Fundamentals of Computer Engineering/Exercise1/full_adder_tb.v
// Full adder testbench
// P W Nutter (based on a design by Jeff Pepper)
// Date 1/9/2020

// Do not touch the following line it is required for simulation 
// #1 = 1ns
`timescale 1ns/100ps 

module full_adder_tb();

// Internal connections
reg a;
reg b;
reg cin;
wire s;
wire cout;

// Instantiate full adder as dut (device under test)

full_adder dut(a, b, cin, s, cout);

// Test vectors
// All combinations required 
initial
 begin
  a = 0; b = 0; cin = 0;
  #100 a = 1;
  #100 a = 0; b = 1;
  #100 a = 1;
  #100 a = 0; b = 0; cin = 1;
  #100 a = 1;
  #100 a = 0; b = 1;
  #100 a = 1;
  #100 $finish; // exit the simulation
 end
 
// Save results as VCD file 
// Do not change
initial
 begin
  $dumpfile("full_adder_tb_results.vcd");  // Save simulation waveforms in this file
  $dumpvars; // Capture all simulation waveforms
 end

endmodule

Year 1/COMP12111 Fundamentals of Computer Engineering/Exercise1/full_adder_tb_results.vcd
$date
	Wed Oct 21 14:35:02 2020
$end
$version
	Icarus Verilog
$end
$timescale
	100ps
$end
$scope module full_adder_tb $end
$var wire 1 ! s $end
$var wire 1 " cout $end
$var reg 1 # a $end
$var reg 1 $ b $end
$var reg 1 % cin $end
$scope module dut $end
$var wire 1 # a $end
$var wire 1 & ab $end
$var wire 1 ' axorb $end
$var wire 1 $ b $end
$var wire 1 % cin $end
$var wire 1 ( cin_axorb $end
$var wire 1 " cout $end
$var wire 1 ! s $end
$upscope $end
$upscope $end
$enddefinitions $end
#0
$dumpvars
x(
x'
x&
0%
0$
0#
x"
x!
$end
#10
0&
0(
0'
#20
0"
0!
#1000
1#
#1010
1'
#1020
1!
#2000
1$
0#
#3000
1#
#3010
0'
1&
#3020
0!
1"
#4000
1%
0$
0#
#4010
1!
0&
#4020
0"
#5000
1#
#5010
1'
#5020
0!
1(
#5030
1"
#6000
1$
0#
#7000
1#
#7010
0'
1&
#7020
1!
0(
